README.md
setup.py
pony_up/__init__.py
pony_up/core.py
pony_up/do_update.py
pony_up/errors.py
pony_up/version_db.py
pony_up.egg-info/PKG-INFO
pony_up.egg-info/SOURCES.txt
pony_up.egg-info/dependency_links.txt
pony_up.egg-info/requires.txt
pony_up.egg-info/top_level.txt