Metadata-Version: 1.1
Name: pony-up
Version: 0.1.1
Summary: Migrations for PonyORM
Home-page: https://github.com/luckydonald/teleflask
Author: luckydonald
Author-email: code@luckydonald.de
License: GPLv3+
Keywords: ponyorm migrations migrate database pony pony_up PonyUp Pony Up!
Platform: UNKNOWN
Classifier: Development Status :: 2 - Pre-Alpha
Classifier: Intended Audience :: Developers
Classifier: Topic :: Database
Classifier: Topic :: Software Development :: Libraries
Classifier: Topic :: Software Development :: Libraries :: Python Modules
Classifier: Environment :: Plugins
Classifier: License :: OSI Approved :: GNU General Public License v3 or later (GPLv3+)
Classifier: Programming Language :: Python :: 2
Classifier: Programming Language :: Python :: 2.7
Classifier: Programming Language :: Python :: 3
Classifier: Programming Language :: Python :: 3.4
Classifier: Programming Language :: Python :: 3.5
Classifier: Programming Language :: Python :: 3.6
Classifier: Operating System :: MacOS :: MacOS X
Classifier: Operating System :: Unix
